hamidreza/__init__.py
hamidreza-0.5.dist-info/licenses/LICENSE
hamidreza-0.5.dist-info/METADATA
hamidreza-0.5.dist-info/WHEEL
hamidreza-0.5.dist-info/top_level.txt
hamidreza-0.5.dist-info/RECORD
