Metadata-Version: 2.4
Name: hamidreza
Version: 0.5
Summary: Personal information and tools by Hamidreza Moghaddam
Home-page: https://hamidrezamoghaddam.ir
Author: Hamidreza Moghaddam
Author-email: h4midrezam@gmail.com
Classifier: Programming Language :: Python :: 3
Classifier: License :: OSI Approved :: MIT License
Classifier: Operating System :: OS Independent
Requires-Python: >=3.6
License-File: LICENSE
Dynamic: author
Dynamic: author-email
Dynamic: classifier
Dynamic: description
Dynamic: description-content-type
Dynamic: home-page
Dynamic: license-file
Dynamic: requires-python
Dynamic: summary
